Metadata-Version: 2.1
Name: mathfin
Version: 0.0.4
Summary: Lib com funções de matematica financeira
Home-page: UNKNOWN
Author: Naoki Yokoyama
Author-email: naokity@msn.com
License: MIT License
Keywords: math fin
Platform: UNKNOWN
License-File: LICENSE
